CHANGES.rst
HOWTO.rst
LICENSE
MANIFEST.in
README.rst
dev.py
setup.py
yieldcurves/__init__.py
yieldcurves/compounding.py
yieldcurves/currency.py
yieldcurves/datecurves.py
yieldcurves/dcfcurves.py
yieldcurves/hullwhite.py
yieldcurves/matrix.py
yieldcurves/nelsonsiegel.py
yieldcurves/operators.py
yieldcurves/optioncurves.py
yieldcurves/optionpricing.py
yieldcurves/tools.py
yieldcurves/yieldcurves.py
yieldcurves.egg-info/PKG-INFO
yieldcurves.egg-info/SOURCES.txt
yieldcurves.egg-info/dependency_links.txt
yieldcurves.egg-info/requires.txt
yieldcurves.egg-info/top_level.txt